[
  {
    "course_family": "BLS",
    "start": "2025-09-20T18:30:00-04:00",
    "city": "Wilmington, NC",
    "url": "https://www.hovn.app/910cpr/sessions/EXAMPLE-BLS-1830",
    "label": "Sep 20, 6:30p • Wilmington"
  },
  {
    "course_family": "BLS",
    "start": "2025-09-22T09:00:00-04:00",
    "city": "Burgaw, NC",
    "url": "https://www.hovn.app/910cpr/sessions/EXAMPLE-BLS-0900"
  },
  {
    "course_family": "ACLS",
    "start": "2025-09-24T09:15:00-04:00",
    "city": "Wilmington, NC",
    "url": "https://www.hovn.app/910cpr/sessions/EXAMPLE-ACLS-0915"
  }
]