{
  "schema_version": "0.1",
  "generated_at": "2026-07-20T11:53:54.446659-04:00",
  "read_only_snapshot": true,
  "calendar_source_id": "amy_availability",
  "calendar_id": "c_94724071aa31a0063fbc48be80fdc73d76e604cad5043ff088156eb97e50be97@group.calendar.google.com",
  "source_type": "google_calendar",
  "source_display_name": "910CPR - Amy Availability",
  "date_range": {
    "start": "2026-07-20T11:53:54.083037-04:00",
    "end": "2026-11-17T11:53:54.083037-04:00",
    "days": 120
  },
  "export_status": "ok",
  "url_source": "derived_public_ics_from_calendar_id",
  "event_count": 0,
  "events": [],
  "warnings": [],
  "skipped": {
    "outside_export_window": 12
  },
  "public_site_affected": false,
  "enrollware_called": false,
  "appointments_created": false,
  "appointment_urls_changed": false,
  "worker_creation_enabled": false
}
